[
  {
    "Mod": {
      "meta_list": [],
      "vs": {
        "Outer": {
          "token": {
            "offset": 0,
            "value": "pub"
          },
          "tail_s": {
            "offset": 3,
            "value": " "
          }
        }
      },
      "keyword": [
        {
          "offset": 4,
          "value": "mod"
        },
        {
          "offset": 7,
          "value": " "
        }
      ],
      "ident": {
        "offset": 8,
        "value": "view"
      },
      "semi_colon": [
        null,
        {
          "offset": 12,
          "value": ";"
        },
        {
          "offset": 13,
          "value": "\n\n"
        }
      ]
    }
  },
  {
    "Mod": {
      "meta_list": [],
      "vs": {
        "Outer": {
          "token": {
            "offset": 15,
            "value": "pub"
          },
          "tail_s": {
            "offset": 18,
            "value": " "
          }
        }
      },
      "keyword": [
        {
          "offset": 19,
          "value": "mod"
        },
        {
          "offset": 22,
          "value": " "
        }
      ],
      "ident": {
        "offset": 23,
        "value": "platform"
      },
      "semi_colon": [
        null,
        {
          "offset": 31,
          "value": ";"
        },
        null
      ]
    }
  }
]